py_crispr_analyser/__init__.py
py_crispr_analyser/align.py
py_crispr_analyser/gather.py
py_crispr_analyser/index.py
py_crispr_analyser/search.py
py_crispr_analyser/utils.py
py_crispr_analyser-1.0.3.dist-info/METADATA
py_crispr_analyser-1.0.3.dist-info/WHEEL
py_crispr_analyser-1.0.3.dist-info/entry_points.txt
py_crispr_analyser-1.0.3.dist-info/licenses/LICENSE
py_crispr_analyser-1.0.3.dist-info/RECORD
